{
  "task_info": {
    "id": 87,
    "user_id": 2,
    "pool_id": 481,
    "cycle_id": 1,
    "partition_idx": 156,
    "num_partitions": 192,
    "status": "queued",
    "progress_json": "{\"phase\": \"queued\", \"phase_msg\": \"等待排程分配...\", \"combos_done\": 1258, \"combos_total\": 1440, \"updated_at\": \"2026-02-26T15:59:13.489829+00:00\", \"best_score\": 264.01448, \"best_candidate_id\": null, \"best_any_score\": 264.01448, \"best_any_metrics\": {\"total_return_pct\": 245.3209, \"max_drawdown_pct\": 9.6057, \"sharpe\": 4.8914, \"trades\": 610, \"win_rate_pct\": 75.082}, \"best_any_params\": {\"family\": \"TEMA_RSI\", \"family_params\": {\"fast_len\": 4, \"slow_len\": 50, \"rsi_len\": 14, \"rsi_thr\": 25, \"tp_pct_strat\": 1.5, \"sl_pct_strat\": 1.5, \"activation_pct\": 0.5, \"trail_ticks\": 200, \"mintick\": 0.1, \"act_max\": 2.0, \"act_step\": 0.5, \"tr_tick_min\": 200, \"tr_tick_max\": 1200, \"tr_tick_step\": 200, \"stake_pct\": 95.0}, \"tp\": 0.0, \"sl\": 0.0, \"max_hold\": 120}, \"best_any_passed\": true, \"best_pass\": [{\"score\": 264.01448, \"params\": {\"family\": \"TEMA_RSI\", \"family_params\": {\"fast_len\": 4, \"slow_len\": 50, \"rsi_len\": 14, \"rsi_thr\": 25, \"tp_pct_strat\": 1.5, \"sl_pct_strat\": 1.5, \"activation_pct\": 0.5, \"trail_ticks\": 200, \"mintick\": 0.1, \"act_max\": 2.0, \"act_step\": 0.5, \"tr_tick_min\": 200, \"tr_tick_max\": 1200, \"tr_tick_step\": 200, \"stake_pct\": 95.0}, \"tp\": 0.0, \"sl\": 0.0, \"max_hold\": 120}, \"metrics\": {\"total_return_pct\": 245.3209, \"max_drawdown_pct\": 9.6057, \"sharpe\": 4.8914, \"trades\": 610, \"win_rate_pct\": 75.082}}, {\"score\": 264.01448, \"params\": {\"family\": \"TEMA_RSI\", \"family_params\": {\"fast_len\": 4, \"slow_len\": 50, \"rsi_len\": 14, \"rsi_thr\": 25, \"tp_pct_strat\": 1.5, \"sl_pct_strat\": 1.5, \"activation_pct\": 0.5, \"trail_ticks\": 200, \"mintick\": 0.1, \"act_max\": 2.0, \"act_step\": 0.5, \"tr_tick_min\": 200, \"tr_tick_max\": 1200, \"tr_tick_step\": 200, \"stake_pct\": 95.0}, \"tp\": 0.0, \"sl\": 0.0, \"max_hold\": 180}, \"metrics\": {\"total_return_pct\": 245.3209, \"max_drawdown_pct\": 9.6057, \"sharpe\": 4.8914, \"trades\": 610, \"win_rate_pct\": 75.082}}, {\"score\": 264.01448, \"params\": {\"family\": \"TEMA_RSI\", \"family_params\": {\"fast_len\": 4, \"slow_len\": 50, \"rsi_len\": 14, \"rsi_thr\": 25, \"tp_pct_strat\": 1.5, \"sl_pct_strat\": 1.5, \"activation_pct\": 0.5, \"trail_ticks\": 200, \"mintick\": 0.1, \"act_max\": 2.0, \"act_step\": 0.5, \"tr_tick_min\": 200, \"tr_tick_max\": 1200, \"tr_tick_step\": 200, \"stake_pct\": 95.0}, \"tp\": 0.0, \"sl\": 0.0, \"max_hold\": 240}, \"metrics\": {\"total_return_pct\": 245.3209, \"max_drawdown_pct\": 9.6057, \"sharpe\": 4.8914, \"trades\": 610, \"win_rate_pct\": 75.082}}, {\"score\": 264.01448, \"params\": {\"family\": \"TEMA_RSI\", \"family_params\": {\"fast_len\": 4, \"slow_len\": 50, \"rsi_len\": 14, \"rsi_thr\": 25, \"tp_pct_strat\": 1.5, \"sl_pct_strat\": 1.5, \"activation_pct\": 0.5, \"trail_ticks\": 200, \"mintick\": 0.1, \"act_max\": 2.0, \"act_step\": 0.5, \"tr_tick_min\": 200, \"tr_tick_max\": 1200, \"tr_tick_step\": 200, \"stake_pct\": 95.0}, \"tp\": 0.0, \"sl\": 0.0, \"max_hold\": 300}, \"metrics\": {\"total_return_pct\": 245.3209, \"max_drawdown_pct\": 9.6057, \"sharpe\": 4.8914, \"trades\": 610, \"win_rate_pct\": 75.082}}, {\"score\": 264.01448, \"params\": {\"family\": \"TEMA_RSI\", \"family_params\": {\"fast_len\": 4, \"slow_len\": 50, \"rsi_len\": 14, \"rsi_thr\": 25, \"tp_pct_strat\": 1.5, \"sl_pct_strat\": 1.5, \"activation_pct\": 0.5, \"trail_ticks\": 200, \"mintick\": 0.1, \"act_max\": 2.0, \"act_step\": 0.5, \"tr_tick_min\": 200, \"tr_tick_max\": 1200, \"tr_tick_step\": 200, \"stake_pct\": 95.0}, \"tp\": 0.0, \"sl\": 0.0, \"max_hold\": 360}, \"metrics\": {\"total_return_pct\": 245.3209, \"max_drawdown_pct\": 9.6057, \"sharpe\": 4.8914, \"trades\": 610, \"win_rate_pct\": 75.082}}, {\"score\": 264.01448, \"params\": {\"family\": \"TEMA_RSI\", \"family_params\": {\"fast_len\": 4, \"slow_len\": 50, \"rsi_len\": 14, \"rsi_thr\": 25, \"tp_pct_strat\": 1.5, \"sl_pct_strat\": 1.5, \"activation_pct\": 0.5, \"trail_ticks\": 200, \"mintick\": 0.1, \"act_max\": 2.0, \"act_step\": 0.5, \"tr_tick_min\": 200, \"tr_tick_max\": 1200, \"tr_tick_step\": 200, \"stake_pct\": 95.0}, \"tp\": 0.0, \"sl\": 0.0, \"max_hold\": 420}, \"metrics\": {\"total_return_pct\": 245.3209, \"max_drawdown_pct\": 9.6057, \"sharpe\": 4.8914, \"trades\": 610, \"win_rate_pct\": 75.082}}, {\"score\": 264.01448, \"params\": {\"family\": \"TEMA_RSI\", \"family_params\": {\"fast_len\": 4, \"slow_len\": 50, \"rsi_len\": 14, \"rsi_thr\": 25, \"tp_pct_strat\": 1.5, \"sl_pct_strat\": 1.5, \"activation_pct\": 0.5, \"trail_ticks\": 200, \"mintick\": 0.1, \"act_max\": 2.0, \"act_step\": 0.5, \"tr_tick_min\": 200, \"tr_tick_max\": 1200, \"tr_tick_step\": 200, \"stake_pct\": 95.0}, \"tp\": 0.0, \"sl\": 0.0, \"max_hold\": 480}, \"metrics\": {\"total_return_pct\": 245.3209, \"max_drawdown_pct\": 9.6057, \"sharpe\": 4.8914, \"trades\": 610, \"win_rate_pct\": 75.082}}, {\"score\": 264.01448, \"params\": {\"family\": \"TEMA_RSI\", \"family_params\": {\"fast_len\": 4, \"slow_len\": 50, \"rsi_len\": 14, \"rsi_thr\": 25, \"tp_pct_strat\": 1.5, \"sl_pct_strat\": 1.5, \"activation_pct\": 0.5, \"trail_ticks\": 200, \"mintick\": 0.1, \"act_max\": 2.0, \"act_step\": 0.5, \"tr_tick_min\": 200, \"tr_tick_max\": 1200, \"tr_tick_step\": 200, \"stake_pct\": 95.0}, \"tp\": 0.0, \"sl\": 0.0, \"max_hold\": 540}, \"metrics\": {\"total_return_pct\": 245.3209, \"max_drawdown_pct\": 9.6057, \"sharpe\": 4.8914, \"trades\": 610, \"win_rate_pct\": 75.082}}, {\"score\": 264.01448, \"params\": {\"family\": \"TEMA_RSI\", \"family_params\": {\"fast_len\": 4, \"slow_len\": 50, \"rsi_len\": 14, \"rsi_thr\": 25, \"tp_pct_strat\": 1.5, \"sl_pct_strat\": 1.5, \"activation_pct\": 0.5, \"trail_ticks\": 200, \"mintick\": 0.1, \"act_max\": 2.0, \"act_step\": 0.5, \"tr_tick_min\": 200, \"tr_tick_max\": 1200, \"tr_tick_step\": 200, \"stake_pct\": 95.0}, \"tp\": 0.0, \"sl\": 0.0, \"max_hold\": 600}, \"metrics\": {\"total_return_pct\": 245.3209, \"max_drawdown_pct\": 9.6057, \"sharpe\": 4.8914, \"trades\": 610, \"win_rate_pct\": 75.082}}, {\"score\": 264.01448, \"params\": {\"family\": \"TEMA_RSI\", \"family_params\": {\"fast_len\": 4, \"slow_len\": 50, \"rsi_len\": 14, \"rsi_thr\": 25, \"tp_pct_strat\": 1.5, \"sl_pct_strat\": 1.5, \"activation_pct\": 0.5, \"trail_ticks\": 200, \"mintick\": 0.1, \"act_max\": 2.0, \"act_step\": 0.5, \"tr_tick_min\": 200, \"tr_tick_max\": 1200, \"tr_tick_step\": 200, \"stake_pct\": 95.0}, \"tp\": 0.0, \"sl\": 0.0, \"max_hold\": 660}, \"metrics\": {\"total_return_pct\": 245.3209, \"max_drawdown_pct\": 9.6057, \"sharpe\": 4.8914, \"trades\": 610, \"win_rate_pct\": 75.082}}, {\"score\": 264.01448, \"params\": {\"family\": \"TEMA_RSI\", \"family_params\": {\"fast_len\": 4, \"slow_len\": 50, \"rsi_len\": 14, \"rsi_thr\": 25, \"tp_pct_strat\": 1.5, \"sl_pct_strat\": 1.5, \"activation_pct\": 0.5, \"trail_ticks\": 200, \"mintick\": 0.1, \"act_max\": 2.0, \"act_step\": 0.5, \"tr_tick_min\": 200, \"tr_tick_max\": 1200, \"tr_tick_step\": 200, \"stake_pct\": 95.0}, \"tp\": 0.0, \"sl\": 0.0, \"max_hold\": 720}, \"metrics\": {\"total_return_pct\": 245.3209, \"max_drawdown_pct\": 9.6057, \"sharpe\": 4.8914, \"trades\": 610, \"win_rate_pct\": 75.082}}, {\"score\": 262.66352, \"params\": {\"family\": \"TEMA_RSI\", \"family_params\": {\"fast_len\": 6, \"slow_len\": 150, \"rsi_len\": 14, \"rsi_thr\": 40, \"tp_pct_strat\": 1.5, \"sl_pct_strat\": 1.5, \"activation_pct\": 0.5, \"trail_ticks\": 200, \"mintick\": 0.1, \"act_max\": 2.0, \"act_step\": 0.5, \"tr_tick_min\": 200, \"tr_tick_max\": 1200, \"tr_tick_step\": 200, \"stake_pct\": 95.0}, \"tp\": 0.0, \"sl\": 0.0, \"max_hold\": 120}, \"metrics\": {\"total_return_pct\": 245.9133, \"max_drawdown_pct\": 14.1713, \"sharpe\": 5.0506, \"trades\": 605, \"win_rate_pct\": 75.5372}}, {\"score\": 262.66352, \"params\": {\"family\": \"TEMA_RSI\", \"family_params\": {\"fast_len\": 6, \"slow_len\": 150, \"rsi_len\": 14, \"rsi_thr\": 40, \"tp_pct_strat\": 1.5, \"sl_pct_strat\": 1.5, \"activation_pct\": 0.5, \"trail_ticks\": 200, \"mintick\": 0.1, \"act_max\": 2.0, \"act_step\": 0.5, \"tr_tick_min\": 200, \"tr_tick_max\": 1200, \"tr_tick_step\": 200, \"stake_pct\": 95.0}, \"tp\": 0.0, \"sl\": 0.0, \"max_hold\": 180}, \"metrics\": {\"total_return_pct\": 245.9133, \"max_drawdown_pct\": 14.1713, \"sharpe\": 5.0506, \"trades\": 605, \"win_rate_pct\": 75.5372}}, {\"score\": 262.66352, \"params\": {\"family\": \"TEMA_RSI\", \"family_params\": {\"fast_len\": 6, \"slow_len\": 150, \"rsi_len\": 14, \"rsi_thr\": 40, \"tp_pct_strat\": 1.5, \"sl_pct_strat\": 1.5, \"activation_pct\": 0.5, \"trail_ticks\": 200, \"mintick\": 0.1, \"act_max\": 2.0, \"act_step\": 0.5, \"tr_tick_min\": 200, \"tr_tick_max\": 1200, \"tr_tick_step\": 200, \"stake_pct\": 95.0}, \"tp\": 0.0, \"sl\": 0.0, \"max_hold\": 240}, \"metrics\": {\"total_return_pct\": 245.9133, \"max_drawdown_pct\": 14.1713, \"sharpe\": 5.0506, \"trades\": 605, \"win_rate_pct\": 75.5372}}, {\"score\": 262.66352, \"params\": {\"family\": \"TEMA_RSI\", \"family_params\": {\"fast_len\": 6, \"slow_len\": 150, \"rsi_len\": 14, \"rsi_thr\": 40, \"tp_pct_strat\": 1.5, \"sl_pct_strat\": 1.5, \"activation_pct\": 0.5, \"trail_ticks\": 200, \"mintick\": 0.1, \"act_max\": 2.0, \"act_step\": 0.5, \"tr_tick_min\": 200, \"tr_tick_max\": 1200, \"tr_tick_step\": 200, \"stake_pct\": 95.0}, \"tp\": 0.0, \"sl\": 0.0, \"max_hold\": 300}, \"metrics\": {\"total_return_pct\": 245.9133, \"max_drawdown_pct\": 14.1713, \"sharpe\": 5.0506, \"trades\": 605, \"win_rate_pct\": 75.5372}}, {\"score\": 262.66352, \"params\": {\"family\": \"TEMA_RSI\", \"family_params\": {\"fast_len\": 6, \"slow_len\": 150, \"rsi_len\": 14, \"rsi_thr\": 40, \"tp_pct_strat\": 1.5, \"sl_pct_strat\": 1.5, \"activation_pct\": 0.5, \"trail_ticks\": 200, \"mintick\": 0.1, \"act_max\": 2.0, \"act_step\": 0.5, \"tr_tick_min\": 200, \"tr_tick_max\": 1200, \"tr_tick_step\": 200, \"stake_pct\": 95.0}, \"tp\": 0.0, \"sl\": 0.0, \"max_hold\": 360}, \"metrics\": {\"total_return_pct\": 245.9133, \"max_drawdown_pct\": 14.1713, \"sharpe\": 5.0506, \"trades\": 605, \"win_rate_pct\": 75.5372}}, {\"score\": 262.66352, \"params\": {\"family\": \"TEMA_RSI\", \"family_params\": {\"fast_len\": 6, \"slow_len\": 150, \"rsi_len\": 14, \"rsi_thr\": 40, \"tp_pct_strat\": 1.5, \"sl_pct_strat\": 1.5, \"activation_pct\": 0.5, \"trail_ticks\": 200, \"mintick\": 0.1, \"act_max\": 2.0, \"act_step\": 0.5, \"tr_tick_min\": 200, \"tr_tick_max\": 1200, \"tr_tick_step\": 200, \"stake_pct\": 95.0}, \"tp\": 0.0, \"sl\": 0.0, \"max_hold\": 420}, \"metrics\": {\"total_return_pct\": 245.9133, \"max_drawdown_pct\": 14.1713, \"sharpe\": 5.0506, \"trades\": 605, \"win_rate_pct\": 75.5372}}, {\"score\": 262.66352, \"params\": {\"family\": \"TEMA_RSI\", \"family_params\": {\"fast_len\": 6, \"slow_len\": 150, \"rsi_len\": 14, \"rsi_thr\": 40, \"tp_pct_strat\": 1.5, \"sl_pct_strat\": 1.5, \"activation_pct\": 0.5, \"trail_ticks\": 200, \"mintick\": 0.1, \"act_max\": 2.0, \"act_step\": 0.5, \"tr_tick_min\": 200, \"tr_tick_max\": 1200, \"tr_tick_step\": 200, \"stake_pct\": 95.0}, \"tp\": 0.0, \"sl\": 0.0, \"max_hold\": 480}, \"metrics\": {\"total_return_pct\": 245.9133, \"max_drawdown_pct\": 14.1713, \"sharpe\": 5.0506, \"trades\": 605, \"win_rate_pct\": 75.5372}}, {\"score\": 262.66352, \"params\": {\"family\": \"TEMA_RSI\", \"family_params\": {\"fast_len\": 6, \"slow_len\": 150, \"rsi_len\": 14, \"rsi_thr\": 40, \"tp_pct_strat\": 1.5, \"sl_pct_strat\": 1.5, \"activation_pct\": 0.5, \"trail_ticks\": 200, \"mintick\": 0.1, \"act_max\": 2.0, \"act_step\": 0.5, \"tr_tick_min\": 200, \"tr_tick_max\": 1200, \"tr_tick_step\": 200, \"stake_pct\": 95.0}, \"tp\": 0.0, \"sl\": 0.0, \"max_hold\": 540}, \"metrics\": {\"total_return_pct\": 245.9133, \"max_drawdown_pct\": 14.1713, \"sharpe\": 5.0506, \"trades\": 605, \"win_rate_pct\": 75.5372}}, {\"score\": 262.66352, \"params\": {\"family\": \"TEMA_RSI\", \"family_params\": {\"fast_len\": 6, \"slow_len\": 150, \"rsi_len\": 14, \"rsi_thr\": 40, \"tp_pct_strat\": 1.5, \"sl_pct_strat\": 1.5, \"activation_pct\": 0.5, \"trail_ticks\": 200, \"mintick\": 0.1, \"act_max\": 2.0, \"act_step\": 0.5, \"tr_tick_min\": 200, \"tr_tick_max\": 1200, \"tr_tick_step\": 200, \"stake_pct\": 95.0}, \"tp\": 0.0, \"sl\": 0.0, \"max_hold\": 600}, \"metrics\": {\"total_return_pct\": 245.9133, \"max_drawdown_pct\": 14.1713, \"sharpe\": 5.0506, \"trades\": 605, \"win_rate_pct\": 75.5372}}, {\"score\": 262.66352, \"params\": {\"family\": \"TEMA_RSI\", \"family_params\": {\"fast_len\": 6, \"slow_len\": 150, \"rsi_len\": 14, \"rsi_thr\": 40, \"tp_pct_strat\": 1.5, \"sl_pct_strat\": 1.5, \"activation_pct\": 0.5, \"trail_ticks\": 200, \"mintick\": 0.1, \"act_max\": 2.0, \"act_step\": 0.5, \"tr_tick_min\": 200, \"tr_tick_max\": 1200, \"tr_tick_step\": 200, \"stake_pct\": 95.0}, \"tp\": 0.0, \"sl\": 0.0, \"max_hold\": 660}, \"metrics\": {\"total_return_pct\": 245.9133, \"max_drawdown_pct\": 14.1713, \"sharpe\": 5.0506, \"trades\": 605, \"win_rate_pct\": 75.5372}}, {\"score\": 262.66352, \"params\": {\"family\": \"TEMA_RSI\", \"family_params\": {\"fast_len\": 6, \"slow_len\": 150, \"rsi_len\": 14, \"rsi_thr\": 40, \"tp_pct_strat\": 1.5, \"sl_pct_strat\": 1.5, \"activation_pct\": 0.5, \"trail_ticks\": 200, \"mintick\": 0.1, \"act_max\": 2.0, \"act_step\": 0.5, \"tr_tick_min\": 200, \"tr_tick_max\": 1200, \"tr_tick_step\": 200, \"stake_pct\": 95.0}, \"tp\": 0.0, \"sl\": 0.0, \"max_hold\": 720}, \"metrics\": {\"total_return_pct\": 245.9133, \"max_drawdown_pct\": 14.1713, \"sharpe\": 5.0506, \"trades\": 605, \"win_rate_pct\": 75.5372}}, {\"score\": 260.21997999999996, \"params\": {\"family\": \"TEMA_RSI\", \"family_params\": {\"fast_len\": 4, \"slow_len\": 50, \"rsi_len\": 14, \"rsi_thr\": 25, \"tp_pct_strat\": 1.5, \"sl_pct_strat\": 1.5, \"activation_pct\": 0.5, \"trail_ticks\": 200, \"mintick\": 0.1, \"act_max\": 2.0, \"act_step\": 0.5, \"tr_tick_min\": 200, \"tr_tick_max\": 1200, \"tr_tick_step\": 200, \"stake_pct\": 95.0}, \"tp\": 0.0, \"sl\": 0.0, \"max_hold\": 60}, \"metrics\": {\"total_return_pct\": 241.7394, \"max_drawdown_pct\": 9.6057, \"sharpe\": 4.8488, \"trades\": 614, \"win_rate_pct\": 74.7557}}, {\"score\": 256.9382, \"params\": {\"family\": \"TEMA_RSI\", \"family_params\": {\"fast_len\": 6, \"slow_len\": 150, \"rsi_len\": 14, \"rsi_thr\": 40, \"tp_pct_strat\": 1.5, \"sl_pct_strat\": 1.5, \"activation_pct\": 0.5, \"trail_ticks\": 200, \"mintick\": 0.1, \"act_max\": 2.0, \"act_step\": 0.5, \"tr_tick_min\": 200, \"tr_tick_max\": 1200, \"tr_tick_step\": 200, \"stake_pct\": 95.0}, \"tp\": 0.0, \"sl\": 0.0, \"max_hold\": 60}, \"metrics\": {\"total_return_pct\": 240.7814, \"max_drawdown_pct\": 14.6445, \"sharpe\": 4.9887, \"trades\": 608, \"win_rate_pct\": 75.1645}}, {\"score\": 245.59186000000003, \"params\": {\"family\": \"TEMA_RSI\", \"family_params\": {\"fast_len\": 6, \"slow_len\": 50, \"rsi_len\": 14, \"rsi_thr\": 40, \"tp_pct_strat\": 1.2, \"sl_pct_strat\": 1.5, \"activation_pct\": 0.5, \"trail_ticks\": 600, \"mintick\": 0.1, \"act_max\": 2.0, \"act_step\": 0.5, \"tr_tick_min\": 200, \"tr_tick_max\": 1200, \"tr_tick_step\": 200, \"stake_pct\": 95.0}, \"tp\": 0.0, \"sl\": 0.0, \"max_hold\": 120}, \"metrics\": {\"total_return_pct\": 230.0593, \"max_drawdown_pct\": 12.8974, \"sharpe\": 4.6542, \"trades\": 652, \"win_rate_pct\": 75.3067}}, {\"score\": 245.59186000000003, \"params\": {\"family\": \"TEMA_RSI\", \"family_params\": {\"fast_len\": 6, \"slow_len\": 50, \"rsi_len\": 14, \"rsi_thr\": 40, \"tp_pct_strat\": 1.2, \"sl_pct_strat\": 1.5, \"activation_pct\": 0.5, \"trail_ticks\": 600, \"mintick\": 0.1, \"act_max\": 2.0, \"act_step\": 0.5, \"tr_tick_min\": 200, \"tr_tick_max\": 1200, \"tr_tick_step\": 200, \"stake_pct\": 95.0}, \"tp\": 0.0, \"sl\": 0.0, \"max_hold\": 180}, \"metrics\": {\"total_return_pct\": 230.0593, \"max_drawdown_pct\": 12.8974, \"sharpe\": 4.6542, \"trades\": 652, \"win_rate_pct\": 75.3067}}, {\"score\": 245.59186000000003, \"params\": {\"family\": \"TEMA_RSI\", \"family_params\": {\"fast_len\": 6, \"slow_len\": 50, \"rsi_len\": 14, \"rsi_thr\": 40, \"tp_pct_strat\": 1.2, \"sl_pct_strat\": 1.5, \"activation_pct\": 0.5, \"trail_ticks\": 600, \"mintick\": 0.1, \"act_max\": 2.0, \"act_step\": 0.5, \"tr_tick_min\": 200, \"tr_tick_max\": 1200, \"tr_tick_step\": 200, \"stake_pct\": 95.0}, \"tp\": 0.0, \"sl\": 0.0, \"max_hold\": 240}, \"metrics\": {\"total_return_pct\": 230.0593, \"max_drawdown_pct\": 12.8974, \"sharpe\": 4.6542, \"trades\": 652, \"win_rate_pct\": 75.3067}}, {\"score\": 245.59186000000003, \"params\": {\"family\": \"TEMA_RSI\", \"family_params\": {\"fast_len\": 6, \"slow_len\": 50, \"rsi_len\": 14, \"rsi_thr\": 40, \"tp_pct_strat\": 1.2, \"sl_pct_strat\": 1.5, \"activation_pct\": 0.5, \"trail_ticks\": 600, \"mintick\": 0.1, \"act_max\": 2.0, \"act_step\": 0.5, \"tr_tick_min\": 200, \"tr_tick_max\": 1200, \"tr_tick_step\": 200, \"stake_pct\": 95.0}, \"tp\": 0.0, \"sl\": 0.0, \"max_hold\": 300}, \"metrics\": {\"total_return_pct\": 230.0593, \"max_drawdown_pct\": 12.8974, \"sharpe\": 4.6542, \"trades\": 652, \"win_rate_pct\": 75.3067}}, {\"score\": 245.59186000000003, \"params\": {\"family\": \"TEMA_RSI\", \"family_params\": {\"fast_len\": 6, \"slow_len\": 50, \"rsi_len\": 14, \"rsi_thr\": 40, \"tp_pct_strat\": 1.2, \"sl_pct_strat\": 1.5, \"activation_pct\": 0.5, \"trail_ticks\": 600, \"mintick\": 0.1, \"act_max\": 2.0, \"act_step\": 0.5, \"tr_tick_min\": 200, \"tr_tick_max\": 1200, \"tr_tick_step\": 200, \"stake_pct\": 95.0}, \"tp\": 0.0, \"sl\": 0.0, \"max_hold\": 360}, \"metrics\": {\"total_return_pct\": 230.0593, \"max_drawdown_pct\": 12.8974, \"sharpe\": 4.6542, \"trades\": 652, \"win_rate_pct\": 75.3067}}, {\"score\": 245.59186000000003, \"params\": {\"family\": \"TEMA_RSI\", \"family_params\": {\"fast_len\": 6, \"slow_len\": 50, \"rsi_len\": 14, \"rsi_thr\": 40, \"tp_pct_strat\": 1.2, \"sl_pct_strat\": 1.5, \"activation_pct\": 0.5, \"trail_ticks\": 600, \"mintick\": 0.1, \"act_max\": 2.0, \"act_step\": 0.5, \"tr_tick_min\": 200, \"tr_tick_max\": 1200, \"tr_tick_step\": 200, \"stake_pct\": 95.0}, \"tp\": 0.0, \"sl\": 0.0, \"max_hold\": 420}, \"metrics\": {\"total_return_pct\": 230.0593, \"max_drawdown_pct\": 12.8974, \"sharpe\": 4.6542, \"trades\": 652, \"win_rate_pct\": 75.3067}}], \"phase_progress\": 0.0, \"last_error\": null, \"elapsed_s\": 30.155, \"speed_cps\": 41.717813, \"eta_s\": 4.363, \"queue_pos\": 1, \"queue_total\": 1}",
    "last_heartbeat": "2026-02-26T15:59:13.500954+00:00",
    "created_at": "2026-02-26T15:56:39.516597+00:00",
    "updated_at": "2026-02-26T15:59:13.500938+00:00",
    "family": "TEMA_RSI",
    "symbol": "BTC_USDT",
    "timeframe_min": 60,
    "years": 1,
    "grid_spec_json": "{\"fast_min\": 3, \"fast_max\": 6, \"fast_step\": 1, \"slow_min\": 50, \"slow_max\": 200, \"slow_step\": 50, \"rsi_thr_min\": 20, \"rsi_thr_max\": 40, \"rsi_thr_step\": 5, \"tp_min\": 0.6, \"tp_max\": 1.5, \"tp_step\": 0.3, \"sl_min\": 1.5, \"sl_max\": 4.5, \"sl_step\": 1.5, \"act_min\": 0.5, \"act_max\": 2.0, \"act_step\": 0.5, \"tr_tick_min\": 200, \"tr_tick_max\": 1200, \"tr_tick_step\": 200, \"mintick\": 0.1, \"stake_pct\": 95.0}",
    "risk_spec_json": "{\"tp_min\": 0.0, \"tp_max\": 0.0, \"tp_step\": 1.0, \"sl_min\": 0.0, \"sl_max\": 0.0, \"sl_step\": 1.0, \"max_hold_min\": 60, \"max_hold_max\": 720, \"max_hold_step\": 60, \"fee_side\": 0.0002, \"slippage\": 0.0, \"worst_case\": true, \"reverse_mode\": false}",
    "seed": 1312784442,
    "pool_name": "TEMA_RSI | BTC_USDT | 1m [BTC_USDT_60m]"
  },
  "timestamp": "2026-02-26T15:59:31.212523+00:00",
  "best_pass_count": 30,
  "candidates": [
    {
      "id": 253,
      "score": 264.01448,
      "params": {
        "family": "TEMA_RSI",
        "family_params": {
          "fast_len": 4,
          "slow_len": 50,
          "rsi_len": 14,
          "rsi_thr": 25,
          "tp_pct_strat": 1.5,
          "sl_pct_strat": 1.5,
          "activation_pct": 0.5,
          "trail_ticks": 200,
          "mintick": 0.1,
          "act_max": 2.0,
          "act_step": 0.5,
          "tr_tick_min": 200,
          "tr_tick_max": 1200,
          "tr_tick_step": 200,
          "stake_pct": 95.0
        },
        "tp": 0.0,
        "sl": 0.0,
        "max_hold": 120
      },
      "metrics": {
        "total_return_pct": 245.3209,
        "max_drawdown_pct": 9.6057,
        "sharpe": 4.8914,
        "trades": 610,
        "win_rate_pct": 75.082
      }
    },
    {
      "id": 254,
      "score": 264.01448,
      "params": {
        "family": "TEMA_RSI",
        "family_params": {
          "fast_len": 4,
          "slow_len": 50,
          "rsi_len": 14,
          "rsi_thr": 25,
          "tp_pct_strat": 1.5,
          "sl_pct_strat": 1.5,
          "activation_pct": 0.5,
          "trail_ticks": 200,
          "mintick": 0.1,
          "act_max": 2.0,
          "act_step": 0.5,
          "tr_tick_min": 200,
          "tr_tick_max": 1200,
          "tr_tick_step": 200,
          "stake_pct": 95.0
        },
        "tp": 0.0,
        "sl": 0.0,
        "max_hold": 180
      },
      "metrics": {
        "total_return_pct": 245.3209,
        "max_drawdown_pct": 9.6057,
        "sharpe": 4.8914,
        "trades": 610,
        "win_rate_pct": 75.082
      }
    },
    {
      "id": 255,
      "score": 264.01448,
      "params": {
        "family": "TEMA_RSI",
        "family_params": {
          "fast_len": 4,
          "slow_len": 50,
          "rsi_len": 14,
          "rsi_thr": 25,
          "tp_pct_strat": 1.5,
          "sl_pct_strat": 1.5,
          "activation_pct": 0.5,
          "trail_ticks": 200,
          "mintick": 0.1,
          "act_max": 2.0,
          "act_step": 0.5,
          "tr_tick_min": 200,
          "tr_tick_max": 1200,
          "tr_tick_step": 200,
          "stake_pct": 95.0
        },
        "tp": 0.0,
        "sl": 0.0,
        "max_hold": 240
      },
      "metrics": {
        "total_return_pct": 245.3209,
        "max_drawdown_pct": 9.6057,
        "sharpe": 4.8914,
        "trades": 610,
        "win_rate_pct": 75.082
      }
    },
    {
      "id": 256,
      "score": 264.01448,
      "params": {
        "family": "TEMA_RSI",
        "family_params": {
          "fast_len": 4,
          "slow_len": 50,
          "rsi_len": 14,
          "rsi_thr": 25,
          "tp_pct_strat": 1.5,
          "sl_pct_strat": 1.5,
          "activation_pct": 0.5,
          "trail_ticks": 200,
          "mintick": 0.1,
          "act_max": 2.0,
          "act_step": 0.5,
          "tr_tick_min": 200,
          "tr_tick_max": 1200,
          "tr_tick_step": 200,
          "stake_pct": 95.0
        },
        "tp": 0.0,
        "sl": 0.0,
        "max_hold": 300
      },
      "metrics": {
        "total_return_pct": 245.3209,
        "max_drawdown_pct": 9.6057,
        "sharpe": 4.8914,
        "trades": 610,
        "win_rate_pct": 75.082
      }
    },
    {
      "id": 257,
      "score": 264.01448,
      "params": {
        "family": "TEMA_RSI",
        "family_params": {
          "fast_len": 4,
          "slow_len": 50,
          "rsi_len": 14,
          "rsi_thr": 25,
          "tp_pct_strat": 1.5,
          "sl_pct_strat": 1.5,
          "activation_pct": 0.5,
          "trail_ticks": 200,
          "mintick": 0.1,
          "act_max": 2.0,
          "act_step": 0.5,
          "tr_tick_min": 200,
          "tr_tick_max": 1200,
          "tr_tick_step": 200,
          "stake_pct": 95.0
        },
        "tp": 0.0,
        "sl": 0.0,
        "max_hold": 360
      },
      "metrics": {
        "total_return_pct": 245.3209,
        "max_drawdown_pct": 9.6057,
        "sharpe": 4.8914,
        "trades": 610,
        "win_rate_pct": 75.082
      }
    },
    {
      "id": 258,
      "score": 264.01448,
      "params": {
        "family": "TEMA_RSI",
        "family_params": {
          "fast_len": 4,
          "slow_len": 50,
          "rsi_len": 14,
          "rsi_thr": 25,
          "tp_pct_strat": 1.5,
          "sl_pct_strat": 1.5,
          "activation_pct": 0.5,
          "trail_ticks": 200,
          "mintick": 0.1,
          "act_max": 2.0,
          "act_step": 0.5,
          "tr_tick_min": 200,
          "tr_tick_max": 1200,
          "tr_tick_step": 200,
          "stake_pct": 95.0
        },
        "tp": 0.0,
        "sl": 0.0,
        "max_hold": 420
      },
      "metrics": {
        "total_return_pct": 245.3209,
        "max_drawdown_pct": 9.6057,
        "sharpe": 4.8914,
        "trades": 610,
        "win_rate_pct": 75.082
      }
    },
    {
      "id": 259,
      "score": 264.01448,
      "params": {
        "family": "TEMA_RSI",
        "family_params": {
          "fast_len": 4,
          "slow_len": 50,
          "rsi_len": 14,
          "rsi_thr": 25,
          "tp_pct_strat": 1.5,
          "sl_pct_strat": 1.5,
          "activation_pct": 0.5,
          "trail_ticks": 200,
          "mintick": 0.1,
          "act_max": 2.0,
          "act_step": 0.5,
          "tr_tick_min": 200,
          "tr_tick_max": 1200,
          "tr_tick_step": 200,
          "stake_pct": 95.0
        },
        "tp": 0.0,
        "sl": 0.0,
        "max_hold": 480
      },
      "metrics": {
        "total_return_pct": 245.3209,
        "max_drawdown_pct": 9.6057,
        "sharpe": 4.8914,
        "trades": 610,
        "win_rate_pct": 75.082
      }
    },
    {
      "id": 260,
      "score": 264.01448,
      "params": {
        "family": "TEMA_RSI",
        "family_params": {
          "fast_len": 4,
          "slow_len": 50,
          "rsi_len": 14,
          "rsi_thr": 25,
          "tp_pct_strat": 1.5,
          "sl_pct_strat": 1.5,
          "activation_pct": 0.5,
          "trail_ticks": 200,
          "mintick": 0.1,
          "act_max": 2.0,
          "act_step": 0.5,
          "tr_tick_min": 200,
          "tr_tick_max": 1200,
          "tr_tick_step": 200,
          "stake_pct": 95.0
        },
        "tp": 0.0,
        "sl": 0.0,
        "max_hold": 540
      },
      "metrics": {
        "total_return_pct": 245.3209,
        "max_drawdown_pct": 9.6057,
        "sharpe": 4.8914,
        "trades": 610,
        "win_rate_pct": 75.082
      }
    },
    {
      "id": 261,
      "score": 264.01448,
      "params": {
        "family": "TEMA_RSI",
        "family_params": {
          "fast_len": 4,
          "slow_len": 50,
          "rsi_len": 14,
          "rsi_thr": 25,
          "tp_pct_strat": 1.5,
          "sl_pct_strat": 1.5,
          "activation_pct": 0.5,
          "trail_ticks": 200,
          "mintick": 0.1,
          "act_max": 2.0,
          "act_step": 0.5,
          "tr_tick_min": 200,
          "tr_tick_max": 1200,
          "tr_tick_step": 200,
          "stake_pct": 95.0
        },
        "tp": 0.0,
        "sl": 0.0,
        "max_hold": 600
      },
      "metrics": {
        "total_return_pct": 245.3209,
        "max_drawdown_pct": 9.6057,
        "sharpe": 4.8914,
        "trades": 610,
        "win_rate_pct": 75.082
      }
    },
    {
      "id": 262,
      "score": 264.01448,
      "params": {
        "family": "TEMA_RSI",
        "family_params": {
          "fast_len": 4,
          "slow_len": 50,
          "rsi_len": 14,
          "rsi_thr": 25,
          "tp_pct_strat": 1.5,
          "sl_pct_strat": 1.5,
          "activation_pct": 0.5,
          "trail_ticks": 200,
          "mintick": 0.1,
          "act_max": 2.0,
          "act_step": 0.5,
          "tr_tick_min": 200,
          "tr_tick_max": 1200,
          "tr_tick_step": 200,
          "stake_pct": 95.0
        },
        "tp": 0.0,
        "sl": 0.0,
        "max_hold": 660
      },
      "metrics": {
        "total_return_pct": 245.3209,
        "max_drawdown_pct": 9.6057,
        "sharpe": 4.8914,
        "trades": 610,
        "win_rate_pct": 75.082
      }
    },
    {
      "id": 263,
      "score": 264.01448,
      "params": {
        "family": "TEMA_RSI",
        "family_params": {
          "fast_len": 4,
          "slow_len": 50,
          "rsi_len": 14,
          "rsi_thr": 25,
          "tp_pct_strat": 1.5,
          "sl_pct_strat": 1.5,
          "activation_pct": 0.5,
          "trail_ticks": 200,
          "mintick": 0.1,
          "act_max": 2.0,
          "act_step": 0.5,
          "tr_tick_min": 200,
          "tr_tick_max": 1200,
          "tr_tick_step": 200,
          "stake_pct": 95.0
        },
        "tp": 0.0,
        "sl": 0.0,
        "max_hold": 720
      },
      "metrics": {
        "total_return_pct": 245.3209,
        "max_drawdown_pct": 9.6057,
        "sharpe": 4.8914,
        "trades": 610,
        "win_rate_pct": 75.082
      }
    },
    {
      "id": 264,
      "score": 264.01448,
      "params": {
        "family": "TEMA_RSI",
        "family_params": {
          "fast_len": 4,
          "slow_len": 50,
          "rsi_len": 14,
          "rsi_thr": 25,
          "tp_pct_strat": 0.6,
          "sl_pct_strat": 1.5,
          "activation_pct": 0.5,
          "trail_ticks": 200,
          "mintick": 0.1,
          "act_max": 2.0,
          "act_step": 0.5,
          "tr_tick_min": 200,
          "tr_tick_max": 1200,
          "tr_tick_step": 200,
          "stake_pct": 95.0
        },
        "tp": 0.0,
        "sl": 0.0,
        "max_hold": 120
      },
      "metrics": {
        "total_return_pct": 245.3209,
        "max_drawdown_pct": 9.6057,
        "sharpe": 4.8914,
        "trades": 610,
        "win_rate_pct": 75.082
      }
    },
    {
      "id": 265,
      "score": 264.01448,
      "params": {
        "family": "TEMA_RSI",
        "family_params": {
          "fast_len": 4,
          "slow_len": 50,
          "rsi_len": 14,
          "rsi_thr": 25,
          "tp_pct_strat": 0.6,
          "sl_pct_strat": 1.5,
          "activation_pct": 0.5,
          "trail_ticks": 200,
          "mintick": 0.1,
          "act_max": 2.0,
          "act_step": 0.5,
          "tr_tick_min": 200,
          "tr_tick_max": 1200,
          "tr_tick_step": 200,
          "stake_pct": 95.0
        },
        "tp": 0.0,
        "sl": 0.0,
        "max_hold": 180
      },
      "metrics": {
        "total_return_pct": 245.3209,
        "max_drawdown_pct": 9.6057,
        "sharpe": 4.8914,
        "trades": 610,
        "win_rate_pct": 75.082
      }
    },
    {
      "id": 266,
      "score": 264.01448,
      "params": {
        "family": "TEMA_RSI",
        "family_params": {
          "fast_len": 4,
          "slow_len": 50,
          "rsi_len": 14,
          "rsi_thr": 25,
          "tp_pct_strat": 0.6,
          "sl_pct_strat": 1.5,
          "activation_pct": 0.5,
          "trail_ticks": 200,
          "mintick": 0.1,
          "act_max": 2.0,
          "act_step": 0.5,
          "tr_tick_min": 200,
          "tr_tick_max": 1200,
          "tr_tick_step": 200,
          "stake_pct": 95.0
        },
        "tp": 0.0,
        "sl": 0.0,
        "max_hold": 240
      },
      "metrics": {
        "total_return_pct": 245.3209,
        "max_drawdown_pct": 9.6057,
        "sharpe": 4.8914,
        "trades": 610,
        "win_rate_pct": 75.082
      }
    },
    {
      "id": 267,
      "score": 264.01448,
      "params": {
        "family": "TEMA_RSI",
        "family_params": {
          "fast_len": 4,
          "slow_len": 50,
          "rsi_len": 14,
          "rsi_thr": 25,
          "tp_pct_strat": 0.6,
          "sl_pct_strat": 1.5,
          "activation_pct": 0.5,
          "trail_ticks": 200,
          "mintick": 0.1,
          "act_max": 2.0,
          "act_step": 0.5,
          "tr_tick_min": 200,
          "tr_tick_max": 1200,
          "tr_tick_step": 200,
          "stake_pct": 95.0
        },
        "tp": 0.0,
        "sl": 0.0,
        "max_hold": 300
      },
      "metrics": {
        "total_return_pct": 245.3209,
        "max_drawdown_pct": 9.6057,
        "sharpe": 4.8914,
        "trades": 610,
        "win_rate_pct": 75.082
      }
    },
    {
      "id": 268,
      "score": 264.01448,
      "params": {
        "family": "TEMA_RSI",
        "family_params": {
          "fast_len": 4,
          "slow_len": 50,
          "rsi_len": 14,
          "rsi_thr": 25,
          "tp_pct_strat": 0.6,
          "sl_pct_strat": 1.5,
          "activation_pct": 0.5,
          "trail_ticks": 200,
          "mintick": 0.1,
          "act_max": 2.0,
          "act_step": 0.5,
          "tr_tick_min": 200,
          "tr_tick_max": 1200,
          "tr_tick_step": 200,
          "stake_pct": 95.0
        },
        "tp": 0.0,
        "sl": 0.0,
        "max_hold": 360
      },
      "metrics": {
        "total_return_pct": 245.3209,
        "max_drawdown_pct": 9.6057,
        "sharpe": 4.8914,
        "trades": 610,
        "win_rate_pct": 75.082
      }
    },
    {
      "id": 269,
      "score": 264.01448,
      "params": {
        "family": "TEMA_RSI",
        "family_params": {
          "fast_len": 4,
          "slow_len": 50,
          "rsi_len": 14,
          "rsi_thr": 25,
          "tp_pct_strat": 0.6,
          "sl_pct_strat": 1.5,
          "activation_pct": 0.5,
          "trail_ticks": 200,
          "mintick": 0.1,
          "act_max": 2.0,
          "act_step": 0.5,
          "tr_tick_min": 200,
          "tr_tick_max": 1200,
          "tr_tick_step": 200,
          "stake_pct": 95.0
        },
        "tp": 0.0,
        "sl": 0.0,
        "max_hold": 420
      },
      "metrics": {
        "total_return_pct": 245.3209,
        "max_drawdown_pct": 9.6057,
        "sharpe": 4.8914,
        "trades": 610,
        "win_rate_pct": 75.082
      }
    },
    {
      "id": 270,
      "score": 264.01448,
      "params": {
        "family": "TEMA_RSI",
        "family_params": {
          "fast_len": 4,
          "slow_len": 50,
          "rsi_len": 14,
          "rsi_thr": 25,
          "tp_pct_strat": 0.6,
          "sl_pct_strat": 1.5,
          "activation_pct": 0.5,
          "trail_ticks": 200,
          "mintick": 0.1,
          "act_max": 2.0,
          "act_step": 0.5,
          "tr_tick_min": 200,
          "tr_tick_max": 1200,
          "tr_tick_step": 200,
          "stake_pct": 95.0
        },
        "tp": 0.0,
        "sl": 0.0,
        "max_hold": 480
      },
      "metrics": {
        "total_return_pct": 245.3209,
        "max_drawdown_pct": 9.6057,
        "sharpe": 4.8914,
        "trades": 610,
        "win_rate_pct": 75.082
      }
    },
    {
      "id": 271,
      "score": 264.01448,
      "params": {
        "family": "TEMA_RSI",
        "family_params": {
          "fast_len": 4,
          "slow_len": 50,
          "rsi_len": 14,
          "rsi_thr": 25,
          "tp_pct_strat": 0.6,
          "sl_pct_strat": 1.5,
          "activation_pct": 0.5,
          "trail_ticks": 200,
          "mintick": 0.1,
          "act_max": 2.0,
          "act_step": 0.5,
          "tr_tick_min": 200,
          "tr_tick_max": 1200,
          "tr_tick_step": 200,
          "stake_pct": 95.0
        },
        "tp": 0.0,
        "sl": 0.0,
        "max_hold": 540
      },
      "metrics": {
        "total_return_pct": 245.3209,
        "max_drawdown_pct": 9.6057,
        "sharpe": 4.8914,
        "trades": 610,
        "win_rate_pct": 75.082
      }
    },
    {
      "id": 272,
      "score": 264.01448,
      "params": {
        "family": "TEMA_RSI",
        "family_params": {
          "fast_len": 4,
          "slow_len": 50,
          "rsi_len": 14,
          "rsi_thr": 25,
          "tp_pct_strat": 0.6,
          "sl_pct_strat": 1.5,
          "activation_pct": 0.5,
          "trail_ticks": 200,
          "mintick": 0.1,
          "act_max": 2.0,
          "act_step": 0.5,
          "tr_tick_min": 200,
          "tr_tick_max": 1200,
          "tr_tick_step": 200,
          "stake_pct": 95.0
        },
        "tp": 0.0,
        "sl": 0.0,
        "max_hold": 600
      },
      "metrics": {
        "total_return_pct": 245.3209,
        "max_drawdown_pct": 9.6057,
        "sharpe": 4.8914,
        "trades": 610,
        "win_rate_pct": 75.082
      }
    },
    {
      "id": 273,
      "score": 264.01448,
      "params": {
        "family": "TEMA_RSI",
        "family_params": {
          "fast_len": 4,
          "slow_len": 50,
          "rsi_len": 14,
          "rsi_thr": 25,
          "tp_pct_strat": 0.6,
          "sl_pct_strat": 1.5,
          "activation_pct": 0.5,
          "trail_ticks": 200,
          "mintick": 0.1,
          "act_max": 2.0,
          "act_step": 0.5,
          "tr_tick_min": 200,
          "tr_tick_max": 1200,
          "tr_tick_step": 200,
          "stake_pct": 95.0
        },
        "tp": 0.0,
        "sl": 0.0,
        "max_hold": 660
      },
      "metrics": {
        "total_return_pct": 245.3209,
        "max_drawdown_pct": 9.6057,
        "sharpe": 4.8914,
        "trades": 610,
        "win_rate_pct": 75.082
      }
    },
    {
      "id": 274,
      "score": 264.01448,
      "params": {
        "family": "TEMA_RSI",
        "family_params": {
          "fast_len": 4,
          "slow_len": 50,
          "rsi_len": 14,
          "rsi_thr": 25,
          "tp_pct_strat": 0.6,
          "sl_pct_strat": 1.5,
          "activation_pct": 0.5,
          "trail_ticks": 200,
          "mintick": 0.1,
          "act_max": 2.0,
          "act_step": 0.5,
          "tr_tick_min": 200,
          "tr_tick_max": 1200,
          "tr_tick_step": 200,
          "stake_pct": 95.0
        },
        "tp": 0.0,
        "sl": 0.0,
        "max_hold": 720
      },
      "metrics": {
        "total_return_pct": 245.3209,
        "max_drawdown_pct": 9.6057,
        "sharpe": 4.8914,
        "trades": 610,
        "win_rate_pct": 75.082
      }
    },
    {
      "id": 275,
      "score": 262.66352,
      "params": {
        "family": "TEMA_RSI",
        "family_params": {
          "fast_len": 6,
          "slow_len": 150,
          "rsi_len": 14,
          "rsi_thr": 40,
          "tp_pct_strat": 1.5,
          "sl_pct_strat": 1.5,
          "activation_pct": 0.5,
          "trail_ticks": 200,
          "mintick": 0.1,
          "act_max": 2.0,
          "act_step": 0.5,
          "tr_tick_min": 200,
          "tr_tick_max": 1200,
          "tr_tick_step": 200,
          "stake_pct": 95.0
        },
        "tp": 0.0,
        "sl": 0.0,
        "max_hold": 120
      },
      "metrics": {
        "total_return_pct": 245.9133,
        "max_drawdown_pct": 14.1713,
        "sharpe": 5.0506,
        "trades": 605,
        "win_rate_pct": 75.5372
      }
    },
    {
      "id": 276,
      "score": 262.66352,
      "params": {
        "family": "TEMA_RSI",
        "family_params": {
          "fast_len": 6,
          "slow_len": 150,
          "rsi_len": 14,
          "rsi_thr": 40,
          "tp_pct_strat": 1.5,
          "sl_pct_strat": 1.5,
          "activation_pct": 0.5,
          "trail_ticks": 200,
          "mintick": 0.1,
          "act_max": 2.0,
          "act_step": 0.5,
          "tr_tick_min": 200,
          "tr_tick_max": 1200,
          "tr_tick_step": 200,
          "stake_pct": 95.0
        },
        "tp": 0.0,
        "sl": 0.0,
        "max_hold": 180
      },
      "metrics": {
        "total_return_pct": 245.9133,
        "max_drawdown_pct": 14.1713,
        "sharpe": 5.0506,
        "trades": 605,
        "win_rate_pct": 75.5372
      }
    },
    {
      "id": 277,
      "score": 262.66352,
      "params": {
        "family": "TEMA_RSI",
        "family_params": {
          "fast_len": 6,
          "slow_len": 150,
          "rsi_len": 14,
          "rsi_thr": 40,
          "tp_pct_strat": 1.5,
          "sl_pct_strat": 1.5,
          "activation_pct": 0.5,
          "trail_ticks": 200,
          "mintick": 0.1,
          "act_max": 2.0,
          "act_step": 0.5,
          "tr_tick_min": 200,
          "tr_tick_max": 1200,
          "tr_tick_step": 200,
          "stake_pct": 95.0
        },
        "tp": 0.0,
        "sl": 0.0,
        "max_hold": 240
      },
      "metrics": {
        "total_return_pct": 245.9133,
        "max_drawdown_pct": 14.1713,
        "sharpe": 5.0506,
        "trades": 605,
        "win_rate_pct": 75.5372
      }
    },
    {
      "id": 278,
      "score": 262.66352,
      "params": {
        "family": "TEMA_RSI",
        "family_params": {
          "fast_len": 6,
          "slow_len": 150,
          "rsi_len": 14,
          "rsi_thr": 40,
          "tp_pct_strat": 1.5,
          "sl_pct_strat": 1.5,
          "activation_pct": 0.5,
          "trail_ticks": 200,
          "mintick": 0.1,
          "act_max": 2.0,
          "act_step": 0.5,
          "tr_tick_min": 200,
          "tr_tick_max": 1200,
          "tr_tick_step": 200,
          "stake_pct": 95.0
        },
        "tp": 0.0,
        "sl": 0.0,
        "max_hold": 300
      },
      "metrics": {
        "total_return_pct": 245.9133,
        "max_drawdown_pct": 14.1713,
        "sharpe": 5.0506,
        "trades": 605,
        "win_rate_pct": 75.5372
      }
    },
    {
      "id": 279,
      "score": 262.66352,
      "params": {
        "family": "TEMA_RSI",
        "family_params": {
          "fast_len": 6,
          "slow_len": 150,
          "rsi_len": 14,
          "rsi_thr": 40,
          "tp_pct_strat": 1.5,
          "sl_pct_strat": 1.5,
          "activation_pct": 0.5,
          "trail_ticks": 200,
          "mintick": 0.1,
          "act_max": 2.0,
          "act_step": 0.5,
          "tr_tick_min": 200,
          "tr_tick_max": 1200,
          "tr_tick_step": 200,
          "stake_pct": 95.0
        },
        "tp": 0.0,
        "sl": 0.0,
        "max_hold": 360
      },
      "metrics": {
        "total_return_pct": 245.9133,
        "max_drawdown_pct": 14.1713,
        "sharpe": 5.0506,
        "trades": 605,
        "win_rate_pct": 75.5372
      }
    },
    {
      "id": 280,
      "score": 262.66352,
      "params": {
        "family": "TEMA_RSI",
        "family_params": {
          "fast_len": 6,
          "slow_len": 150,
          "rsi_len": 14,
          "rsi_thr": 40,
          "tp_pct_strat": 1.5,
          "sl_pct_strat": 1.5,
          "activation_pct": 0.5,
          "trail_ticks": 200,
          "mintick": 0.1,
          "act_max": 2.0,
          "act_step": 0.5,
          "tr_tick_min": 200,
          "tr_tick_max": 1200,
          "tr_tick_step": 200,
          "stake_pct": 95.0
        },
        "tp": 0.0,
        "sl": 0.0,
        "max_hold": 420
      },
      "metrics": {
        "total_return_pct": 245.9133,
        "max_drawdown_pct": 14.1713,
        "sharpe": 5.0506,
        "trades": 605,
        "win_rate_pct": 75.5372
      }
    },
    {
      "id": 281,
      "score": 262.66352,
      "params": {
        "family": "TEMA_RSI",
        "family_params": {
          "fast_len": 6,
          "slow_len": 150,
          "rsi_len": 14,
          "rsi_thr": 40,
          "tp_pct_strat": 1.5,
          "sl_pct_strat": 1.5,
          "activation_pct": 0.5,
          "trail_ticks": 200,
          "mintick": 0.1,
          "act_max": 2.0,
          "act_step": 0.5,
          "tr_tick_min": 200,
          "tr_tick_max": 1200,
          "tr_tick_step": 200,
          "stake_pct": 95.0
        },
        "tp": 0.0,
        "sl": 0.0,
        "max_hold": 480
      },
      "metrics": {
        "total_return_pct": 245.9133,
        "max_drawdown_pct": 14.1713,
        "sharpe": 5.0506,
        "trades": 605,
        "win_rate_pct": 75.5372
      }
    },
    {
      "id": 282,
      "score": 262.66352,
      "params": {
        "family": "TEMA_RSI",
        "family_params": {
          "fast_len": 6,
          "slow_len": 150,
          "rsi_len": 14,
          "rsi_thr": 40,
          "tp_pct_strat": 1.5,
          "sl_pct_strat": 1.5,
          "activation_pct": 0.5,
          "trail_ticks": 200,
          "mintick": 0.1,
          "act_max": 2.0,
          "act_step": 0.5,
          "tr_tick_min": 200,
          "tr_tick_max": 1200,
          "tr_tick_step": 200,
          "stake_pct": 95.0
        },
        "tp": 0.0,
        "sl": 0.0,
        "max_hold": 540
      },
      "metrics": {
        "total_return_pct": 245.9133,
        "max_drawdown_pct": 14.1713,
        "sharpe": 5.0506,
        "trades": 605,
        "win_rate_pct": 75.5372
      }
    }
  ]
}